ocean_model_skill_assessor/CLI.py
ocean_model_skill_assessor/__init__.py
ocean_model_skill_assessor/accessor.py
ocean_model_skill_assessor/featuretype.py
ocean_model_skill_assessor/main.py
ocean_model_skill_assessor/paths.py
ocean_model_skill_assessor/stats.py
ocean_model_skill_assessor/utils.py
ocean_model_skill_assessor/plot/__init__.py
ocean_model_skill_assessor/plot/line.py
ocean_model_skill_assessor/plot/map.py
ocean_model_skill_assessor/plot/quiver.py
ocean_model_skill_assessor/plot/surface.py
ocean_model_skill_assessor/vocab/erddap_coastwatch.json
ocean_model_skill_assessor/vocab/erddap_ioos.json
ocean_model_skill_assessor/vocab/general.json
ocean_model_skill_assessor/vocab/standard_names.json
ocean_model_skill_assessor/vocab/vocab_labels.json
ocean_model_skill_assessor-1.3.2.dist-info/LICENSE.txt
ocean_model_skill_assessor-1.3.2.dist-info/METADATA
ocean_model_skill_assessor-1.3.2.dist-info/WHEEL
ocean_model_skill_assessor-1.3.2.dist-info/entry_points.txt
ocean_model_skill_assessor-1.3.2.dist-info/top_level.txt
ocean_model_skill_assessor-1.3.2.dist-info/RECORD
