Metadata-Version: 2.1
Name: ocean-model-skill-assessor
Version: 1.3.2
Summary: A package to fully run the comparison between data and model to assess model skill.
Home-page: https://github.com/axiom-data-science/ocean-model-skill-assessor
Author: Axiom Data Science
Author-email: kristen@axds.co
License: MIT
Classifier: Development Status :: 5 - Production/Stable
Classifier: Topic :: Scientific/Engineering
Classifier: Intended Audience :: Science/Research
Classifier: Operating System :: OS Independent
Classifier: Programming Language :: Python
Classifier: Programming Language :: Python :: 3
Classifier: Programming Language :: Python :: 3.8
Classifier: Programming Language :: Python :: 3.9
Classifier: Programming Language :: Python :: 3.10
Classifier: License :: OSI Approved :: MIT License
Requires-Python: >=3.8
License-File: LICENSE.txt
Requires-Dist: aiohttp
Requires-Dist: alphashape
Requires-Dist: cf-pandas
Requires-Dist: cf-xarray
Requires-Dist: extract-model
Requires-Dist: intake
Requires-Dist: intake-axds
Requires-Dist: intake-erddap
Requires-Dist: intake-xarray
Requires-Dist: matplotlib
Requires-Dist: numpy
Requires-Dist: pandas
Requires-Dist: requests
Requires-Dist: scipy
Requires-Dist: tqdm
Requires-Dist: xarray
